Workbook

Sheet Sheet1
A1: 销售编号 | B1: 产品编号 | C1: 产品名称 | D1: 销售日期 | E1: 销售数量 | F1: 单价 | G1: 总金额 | H1: 销售门店 | I1: 产品类别 | J1: 付款方式
A2: 1 | B2: P001 | C2: 华为P60 Pro | D2: 45505 | E2: 2 | F2: 4999 | G2: =E2*F2 -> 9998 | H2: 门店A | I2: =VLOOKUP(C2,库存表!$B$3:$C$33,2,FALSE) -> 智能手机 | J2: 信用卡
A3: 2 | B3: P002 | C3: 华为Mate 60 | D3: 45506 | E3: 1 | F3: 6999 | G3: =E3*F3 -> 6999 | H3: 门店B | I3: =VLOOKUP(C3,库存表!$B$3:$C$33,2,FALSE) -> 智能手机 | J3: 现金
A4: 3 | B4: P003 | C4: 华为MatePad 11 | D4: 45507 | E4: 3 | F4: 2999 | G4: =E4*F4 -> 8997 | H4: 门店C | I4: =VLOOKUP(C4,库存表!$B$3:$C$33,2,FALSE) -> 平板电脑 | J4: 微信支付
A5: 4 | B5: P004 | C5: 华为Watch GT3 | D5: 45508 | E5: 5 | F5: 1399 | G5: =E5*F5 -> 6995 | H5: 门店A | I5: =VLOOKUP(C5,库存表!$B$3:$C$33,2,FALSE) -> 智能手表 | J5: 信用卡
A6: 5 | B6: P005 | C6: 华为FreeBuds Pro | D6: 45509 | E6: 4 | F6: 1199 | G6: =E6*F6 -> 4796 | H6: 门店B | I6: =VLOOKUP(C6,库存表!$B$3:$C$33,2,FALSE) -> 耳机 | J6: 支付宝
A7: 6 | B7: P006 | C7: 华为MateBook 14 | D7: 45510 | E7: 2 | F7: 7499 | G7: =E7*F7 -> 14998 | H7: 门店C | I7: =VLOOKUP(C7,库存表!$B$3:$C$33,2,FALSE) -> 笔记本电脑 | J7: 现金
A8: 7 | B8: P007 | C8: 华为P60 | D8: 45511 | E8: 1 | F8: 4999 | G8: =E8*F8 -> 4999 | H8: 门店A | I8: =VLOOKUP(C8,库存表!$B$3:$C$33,2,FALSE) -> 智能手机 | J8: 微信支付
A9: 8 | B9: P008 | C9: 华为Mate X2 | D9: 45512 | E9: 1 | F9: 16999 | G9: =E9*F9 -> 16999 | H9: 门店B | I9: =VLOOKUP(C9,库存表!$B$3:$C$33,2,FALSE) -> 智能手机 | J9: 信用卡
A10: 9 | B10: P009 | C10: 华为Watch Fit | D10: 45513 | E10: 6 | F10: 699 | G10: =E10*F10 -> 4194 | H10: 门店C | I10: =VLOOKUP(C10,库存表!$B$3:$C$33,2,FALSE) -> 智能手表 | J10: 支付宝
A11: 10 | B11: P010 | C11: 华为MatePad Pro | D11: 45514 | E11: 1 | F11: 3999 | G11: =E11*F11 -> 3999 | H11: 门店A | I11: =VLOOKUP(C11,库存表!$B$3:$C$33,2,FALSE) -> 平板电脑 | J11: 信用卡
A12: 11 | B12: P011 | C12: 华为P40 | D12: 45515 | E12: 3 | F12: 3999 | G12: =E12*F12 -> 11997 | H12: 门店B | I12: =VLOOKUP(C12,库存表!$B$3:$C$33,2,FALSE) -> 智能手机 | J12: 现金
A13: 12 | B13: P012 | C13: 华为FreeBuds 4 | D13: 45516 | E13: 2 | F13: 799 | G13: =E13*F13 -> 1598 | H13: 门店C | I13: =VLOOKUP(C13,库存表!$B$3:$C$33,2,FALSE) -> 耳机 | J13: 微信支付
... A61: 60 | B61: P005 | C61: 华为FreeBuds Pro | D61: 45508 | E61: 4 | F61: 1199 | G61: =E61*F61 -> 4796 | H61: 门店B | I61: =VLOOKUP(C61,库存表!$B$3:$C$33,2,FALSE) -> 耳机 | J61: 支付宝

Sheet 库存表
A1: 026仓库华为产品统计情况
A3: 产品编号 | B3: 产品名称 | C3: 产品类别 | D3: 单价 | E3: 库存 | F3: 是否缺货
A4: P001 | B4: 华为P60 Pro | C4: 智能手机 | D4: 4999 | E4: 50 | F4: =IF(E4<50,"缺货","不缺货") -> 不缺货
A5: P002 | B5: 华为Mate 60 | C5: 智能手机 | D5: 6999 | E5: 30 | F5: =IF(E5<50,"缺货","不缺货") -> 缺货
A6: P003 | B6: 华为MatePad 11 | C6: 平板电脑 | D6: 2999 | E6: 70 | F6: =IF(E6<50,"缺货","不缺货") -> 不缺货
A7: P004 | B7: 华为Watch GT3 | C7: 智能手表 | D7: 1399 | E7: 60 | F7: =IF(E7<50,"缺货","不缺货") -> 不缺货
A8: P005 | B8: 华为FreeBuds Pro | C8: 耳机 | D8: 1199 | E8: 80 | F8: =IF(E8<50,"缺货","不缺货") -> 不缺货
A9: P006 | B9: 华为MateBook 14 | C9: 笔记本电脑 | D9: 7499 | E9: 40 | F9: =IF(E9<50,"缺货","不缺货") -> 缺货
A10: P007 | B10: 华为P60 | C10: 智能手机 | D10: 4999 | E10: 50 | F10: =IF(E10<50,"缺货","不缺货") -> 不缺货
A11: P008 | B11: 华为Mate X2 | C11: 智能手机 | D11: 16999 | E11: 20 | F11: =IF(E11<50,"缺货","不缺货") -> 缺货
A12: P009 | B12: 华为Watch Fit | C12: 智能手表 | D12: 699 | E12: 90 | F12: =IF(E12<50,"缺货","不缺货") -> 不缺货
A13: P010 | B13: 华为MatePad Pro | C13: 平板电脑 | D13: 3999 | E13: 50 | F13: =IF(E13<50,"缺货","不缺货") -> 不缺货
A14: P011 | B14: 华为P40 | C14: 智能手机 | D14: 3999 | E14: 40 | F14: =IF(E14<50,"缺货","不缺货") -> 缺货
A15: P012 | B15: 华为FreeBuds 4 | C15: 耳机 | D15: 799 | E15: 60 | F15: =IF(E15<50,"缺货","不缺货") -> 不缺货
... A33: P030 | B33: 华为FreeBuds 3 | C33: 耳机 | D33: 799 | E33: 50 | F33: =IF(E33<50,"缺货","不缺货") -> 不缺货

Sheet Sheet3
A1: 产品名称 | B1: 总金额 | C1: 销售门店
A2: 华为P60 Pro | B2: 9998 | C2: 门店A
A3: 华为Watch GT3 | B3: 6995 | C3: 门店A
A4: 华为P60 | B4: 4999 | C4: 门店A
A5: 华为MatePad Pro | B5: 3999 | C5: 门店A
A6: 华为MateBook X | B6: 9999 | C6: 门店A
A7: 华为Mate 40 | B7: 12998 | C7: 门店A
A8: 华为Watch GT 2 Pro | B8: 1699 | C8: 门店A
A9: 华为P20 | B9: 8997 | C9: 门店A
A10: 华为P40 Lite | B10: 12495 | C10: 门店A
A11: 华为MateBook 16 | B11: 8499 | C11: 门店A
A12: 华为Watch GT 2 Pro | B12: 1699 | C12: 门店A
A13: 华为P20 | B13: 8997 | C13: 门店A
... A61: 华为MateBook 14 | B61: 14998 | C61: 门店C

Sheet Sheet4
A1: 付款方式 | B1: 现金
A3: 产品名称 | B3: 平均值项:单价
A4: 华为FreeBuds 4i | B4: 399
A5: 华为Mate 20 | B5: 3499
A6: 华为Mate 60 | B6: 6999
A7: 华为MateBook 14 | B7: 7499
A8: 华为MateBook 16 | B8: 8499
A9: 华为P40 | B9: 3999
A10: 华为Watch GT 2 | B10: 1299
A11: 总计 | B11: 4341.8571
